README.rst
setup.py
corestack/__init__.py
corestack/alarms.py
corestack/auth.py
corestack/blueprints.py
corestack/create_alarm.py
corestack/create_environment.py
corestack/create_inventory.py
corestack/create_schedule.py
corestack/delete_alarm.py
corestack/delete_environment.py
corestack/delete_inventory.py
corestack/delete_schedule.py
corestack/delete_service_account.py
corestack/enginepolicies.py
corestack/environments.py
corestack/execute_blueprint.py
corestack/execute_policy.py
corestack/execute_script.py
corestack/execute_template.py
corestack/inventories.py
corestack/jobs.py
corestack/main.py
corestack/rerun_job.py
corestack/schedules.py
corestack/scripts.py
corestack/service_accounts.py
corestack/show_alarm.py
corestack/show_blueprint.py
corestack/show_enginepolicy.py
corestack/show_environment.py
corestack/show_inventory.py
corestack/show_job.py
corestack/show_schedule.py
corestack/show_script.py
corestack/show_serviceaccount.py
corestack/show_template.py
corestack/templates.py
corestack/tenants.py
corestack.egg-info/PKG-INFO
corestack.egg-info/SOURCES.txt
corestack.egg-info/dependency_links.txt
corestack.egg-info/entry_points.txt
corestack.egg-info/namespace_packages.txt
corestack.egg-info/not-zip-safe
corestack.egg-info/requires.txt
corestack.egg-info/top_level.txt